Workbook

Sheet Léeme
A1: Merk1 · Plantilla de carga mensual
A3: Un solo archivo por mes. Puede traer una o varias marcas: cada fila dice a qué empresa y mes pertenece.
A4: Ejemplo precargado: ELECTROMA · Septiembre 2026. Las líneas 003, 006 y 023 conservan código de agosto porque son campañas que siguieron corriendo; ELE2608-002 es un arrastre de agosto sin plan.
A6: Hojas que Merk1 lee (no cambiar nombres de hojas ni de columnas):
A7: • Mes: tipo de cambio de cada empresa y mes.
A8: • Presupuesto: saldo anterior y presupuesto del mes por partida.
A9: • Calendario: actividades de oferta del mes.
A10: • KPIs: valores reales de años anteriores y meta del año, por KPI.
A11: • Plan: una fila por línea del plan de medios.
A13: Reglas
A14: • Fechas como fecha real (AAAA-MM-DD). Mes como texto AAAA-MM.
A15: • empresa_codigo, medio, objetivo, actividad y partida deben existir en la hoja Catálogos (listas desplegables).
... A20: • Texto azul = dato capturado.

Sheet Mes
A1: empresa_codigo | B1: mes | C1: tipo_cambio
A2: ELE | B2: 2026-09 | C2: 7.85

Sheet Presupuesto
A1: empresa_codigo | B1: mes | C1: partida | D1: saldo_anterior | E1: presupuesto_mes | F1: moneda
A2: ELE | B2: 2026-09 | C2: Meta FB e IG | D2: 7672.46 | E2: 23000 | F2: GTQ
A3: ELE | B3: 2026-09 | C3: Google | D3: -9351.81 | E3: 13268.89 | F3: GTQ
A4: ELE | B4: 2026-09 | C4: YouTube | D4: -12879.55 | E4: 3922.22 | F4: GTQ
A5: ELE | B5: 2026-09 | C5: LinkedIn | D5: 7000.62 | E5: 2000 | F5: GTQ
A6: ELE | B6: 2026-09 | C6: Programatic | D6: -1013.33 | E6: 2285.71 | F6: GTQ
A7: ELE | B7: 2026-09 | C7: Claro SMS | D7: -1089.28 | E7: 480 | F7: GTQ
A8: ELE | B8: 2026-09 | C8: Whatsapp Isoft | D8: -8807.52 | E8: 5000 | F8: GTQ
A9: ELE | B9: 2026-09 | C9: Tik Tok | D9: 8846.2 | E9: 3973.33 | F9: GTQ
A10: ELE | B10: 2026-09 | C10: Leads B2B | D10: 9566.46 | E10: 3571.43 | F10: GTQ
A11: ELE | B11: 2026-09 | C11: Tráfico a tiendas Geolocalizado | D11: 3789.33 | E11: 3571.43 | F11: GTQ
A12: ELE | B12: 2026-09 | C12: Mundial | D12: -4057.26 | E12: 0 | F12: GTQ
A13: ELE | B13: 2026-09 | C13: Extras | D13: 0 | E13: 0 | F13: GTQ

Sheet Calendario
A1: empresa_codigo | B1: mes | C1: actividad | D1: fecha_inicio | E1: fecha_fin | F1: notas
A2: ELE | B2: 2026-09 | C2: Revelación Electro Independencia | D2: 46275 | E2: 46275
A3: ELE | B3: 2026-09 | C3: Leads B2B | D3: 46280 | E3: 46295
A4: ELE | B4: 2026-09 | C4: Electro Independencia | D4: 46281 | E4: 46284
A5: ELE | B5: 2026-09 | C5: Electro Days | D5: 46285 | E5: 46291
A6: ELE | B6: 2026-09 | C6: Promo CC | D6: 46286 | E6: 46291
A7: ELE | B7: 2026-09 | C7: Sale Capacitación | D7: 46288 | E7: 46288
A8: ELE | B8: 2026-09 | C8: Envío de capacitación | D8: 46294 | E8: 46294
A9: ELE | B9: 2026-09 | C9: Capacitación | D9: 46294 | E9: 46294

Sheet KPIs
A1: empresa_codigo | B1: mes | C1: kpi | D1: anio | E1: valor | F1: tipo
A2: ELE | B2: 2026-09 | C2: Alcance | D2: 2024 | E2: 5136036 | F2: Real
A3: ELE | B3: 2026-09 | C3: Alcance | D3: 2025 | E3: 8773997 | F3: Real
A4: ELE | B4: 2026-09 | C4: Alcance | D4: 2026 | F4: Meta
A5: ELE | B5: 2026-09 | C5: MQLs | D5: 2024 | E5: 5958 | F5: Real
A6: ELE | B6: 2026-09 | C6: MQLs | D6: 2025 | E6: 15335 | F6: Real
A7: ELE | B7: 2026-09 | C7: MQLs | D7: 2026 | F7: Meta
A8: ELE | B8: 2026-09 | C8: Interacción | D8: 2024 | E8: 215696 | F8: Real
A9: ELE | B9: 2026-09 | C9: Interacción | D9: 2025 | E9: 259094 | F9: Real
A10: ELE | B10: 2026-09 | C10: Interacción | D10: 2026 | F10: Meta
A11: ELE | B11: 2026-09 | C11: Usuarios web | D11: 2024 | E11: 59879 | F11: Real
A12: ELE | B12: 2026-09 | C12: Usuarios web | D12: 2025 | E12: 96062 | F12: Real
A13: ELE | B13: 2026-09 | C13: Usuarios web | D13: 2026 | F13: Meta
A15: Las metas 2026 venían vacías en el Excel original: llenarlas en las filas tipo Meta.

Sheet Plan
A1: codigo | B1: empresa_codigo | C1: mes | D1: plan | E1: nombre_plan_extra | F1: actividad | G1: fecha_inicio | H1: fecha_fin | I1: fechas_envio | J1: medio | K1: objetivo | L1: partida | M1: inversion | N1: moneda | O1: costo_estimado | P1: proyectado_manual | Q1: tipo_costo (ayuda) | R1: nombre_campana (ayuda)
A2: ELE2609-001 | B2: ELE | C2: 2026-09 | D2: Principal | F2: Mantenimiento | G2: 46266 | H2: 46295 | J2: Meta | K2: Alcance | L2: Meta FB e IG | M2: 2000 | N2: GTQ | O2: 2.85 | Q2: =IFERROR(VLOOKUP(K2,Catálogos!$F:$G,2,FALSE()),"Revisar objetivo") -> Por mil | R2: =A2&" | "&F2&" | "&J2&" | "&K2 -> ELE2609-001 | Mantenimiento | Meta | Alcance
A3: ELE2609-002 | B3: ELE | C3: 2026-09 | D3: Principal | F3: Mantenimiento | G3: 46266 | H3: 46295 | J3: Meta | K3: Interacción | L3: Meta FB e IG | M3: 2715 | N3: GTQ | O3: 0.3 | Q3: =IFERROR(VLOOKUP(K3,Catálogos!$F:$G,2,FALSE()),"Revisar objetivo") -> Por unidad | R3: =A3&" | "&F3&" | "&J3&" | "&K3 -> ELE2609-002 | Mantenimiento | Meta | Interacción
A4: ELE2608-003 | B4: ELE | C4: 2026-09 | D4: Principal | F4: Mantenimiento | G4: 46266 | H4: 46295 | J4: Google Ads | K4: Search · Clics | L4: Google | M4: 3500 | N4: GTQ | O4: 0.65 | Q4: =IFERROR(VLOOKUP(K4,Catálogos!$F:$G,2,FALSE()),"Revisar objetivo") -> Por unidad | R4: =A4&" | "&F4&" | "&J4&" | "&K4 -> ELE2608-003 | Mantenimiento | Google Ads | Search · Clics
A5: ELE2609-004 | B5: ELE | C5: 2026-09 | D5: Principal | F5: Mantenimiento | G5: 46266 | H5: 46295 | J5: TikTok | K5: Alcance | L5: Tik Tok | M5: 2000 | N5: GTQ | O5: 2.4 | Q5: =IFERROR(VLOOKUP(K5,Catálogos!$F:$G,2,FALSE()),"Revisar objetivo") -> Por mil | R5: =A5&" | "&F5&" | "&J5&" | "&K5 -> ELE2609-004 | Mantenimiento | TikTok | Alcance
A6: ELE2608-006 | B6: ELE | C6: 2026-09 | D6: Principal | F6: Apoyo CC | G6: 46266 | H6: 46295 | J6: Meta | K6: Mensajes WhatsApp | L6: Meta FB e IG | M6: 3500 | N6: GTQ | O6: 2.4 | Q6: =IFERROR(VLOOKUP(K6,Catálogos!$F:$G,2,FALSE()),"Revisar objetivo") -> Por unidad | R6: =A6&" | "&F6&" | "&J6&" | "&K6 -> ELE2608-006 | Apoyo CC | Meta | Mensajes WhatsApp
A7: ELE2609-006 | B7: ELE | C7: 2026-09 | D7: Principal | F7: Promo CC | G7: 46286 | H7: 46291 | J7: Meta | K7: Mensajes WhatsApp | L7: Meta FB e IG | M7: 2000.02 | N7: GTQ | O7: 4 | Q7: =IFERROR(VLOOKUP(K7,Catálogos!$F:$G,2,FALSE()),"Revisar objetivo") -> Por unidad | R7: =A7&" | "&F7&" | "&J7&" | "&K7 -> ELE2609-006 | Promo CC | Meta | Mensajes WhatsApp
A8: ELE2609-007 | B8: ELE | C8: 2026-09 | D8: Principal | F8: Electro Independencia | G8: 46275 | H8: 46284 | J8: Meta | K8: Alcance geolocalizado | L8: Meta FB e IG | M8: 12000 | N8: GTQ | O8: 3.9 | Q8: =IFERROR(VLOOKUP(K8,Catálogos!$F:$G,2,FALSE()),"Revisar objetivo") -> Por mil | R8: =A8&" | "&F8&" | "&J8&" | "&K8 -> ELE2609-007 | Electro Independencia | Meta | Alcance geolocalizado
A9: ELE2609-008 | B9: ELE | C9: 2026-09 | D9: Principal | F9: Electro Independencia | G9: 46278 | H9: 46284 | J9: TikTok | K9: Alcance / Video view | L9: Tik Tok | M9: 6454.18 | N9: GTQ | O9: 2.4 | Q9: =IFERROR(VLOOKUP(K9,Catálogos!$F:$G,2,FALSE()),"Revisar objetivo") -> Por mil | R9: =A9&" | "&F9&" | "&J9&" | "&K9 -> ELE2609-008 | Electro Independencia | TikTok | Alcance / Video view
A10: ELE2609-009 | B10: ELE | C10: 2026-09 | D10: Principal | F10: Electro Independencia | G10: 46278 | H10: 46284 | J10: YouTube | K10: Bumper / Instream | L10: YouTube | M10: 5000 | N10: GTQ | O10: 3.5 | Q10: =IFERROR(VLOOKUP(K10,Catálogos!$F:$G,2,FALSE()),"Revisar objetivo") -> Por mil | R10: =A10&" | "&F10&" | "&J10&" | "&K10 -> ELE2609-009 | Electro Independencia | YouTube | Bumper / Instream
A11: ELE2609-010 | B11: ELE | C11: 2026-09 | D11: Principal | F11: Electro Independencia | G11: 46278 | H11: 46284 | J11: Basis | K11: Display programático | L11: Programatic | M11: 4300 | N11: GTQ | O11: 6.19 | Q11: =IFERROR(VLOOKUP(K11,Catálogos!$F:$G,2,FALSE()),"Revisar objetivo") -> Por mil | R11: =A11&" | "&F11&" | "&J11&" | "&K11 -> ELE2609-010 | Electro Independencia | Basis | Display programático
A12: ELE2609-011 | B12: ELE | C12: 2026-09 | D12: Principal | F12: Electro Independencia | G12: 46278 | H12: 46284 | J12: Google Ads | K12: Demand Gen · Alcance | L12: Google | M12: 2756.61 | N12: GTQ | O12: 7.82 | Q12: =IFERROR(VLOOKUP(K12,Catálogos!$F:$G,2,FALSE()),"Revisar objetivo") -> Por mil | R12: =A12&" | "&F12&" | "&J12&" | "&K12 -> ELE2609-011 | Electro Independencia | Google Ads | Demand Gen · Alcance
A13: ELE2609-012 | B13: ELE | C13: 2026-09 | D13: Principal | F13: Electro Independencia | G13: 46280 | H13: 46280 | J13: Claro | K13: SMS geolocalizado | L13: Programatic | M13: 1000 | N13: GTQ | O13: 77 | Q13: =IFERROR(VLOOKUP(K13,Catálogos!$F:$G,2,FALSE()),"Revisar objetivo") -> Por mil | R13: =A13&" | "&F13&" | "&J13&" | "&K13 -> ELE2609-012 | Electro Independencia | Claro | SMS geolocalizado
A14: ELE2609-013 | B14: ELE | C14: 2026-09 | D14: Principal | F14: Electro Independencia | G14: 46282 | H14: 46282 | J14: Claro | K14: SMS geolocalizado | L14: Programatic | M14: 1000 | N14: GTQ | O14: 77 | Q14: =IFERROR(VLOOKUP(K14,Catálogos!$F:$G,2,FALSE()),"Revisar objetivo") -> Por mil | R14: =A14&" | "&F14&" | "&J14&" | "&K14 -> ELE2609-013 | Electro Independencia | Claro | SMS geolocalizado
A15: ELE2609-014 | B15: ELE | C15: 2026-09 | D15: Principal | F15: Electro Independencia | G15: 46278 | H15: 46282 | I15: 13 y 17 | J15: iSoft | K15: WhatsApp masivo | L15: Whatsapp Isoft | M15: 2800 | N15: GTQ | O15: 0.71 | Q15: =IFERROR(VLOOKUP(K15,Catálogos!$F:$G,2,FALSE()),"Revisar objetivo") -> Por unidad | R15: =A15&" | "&F15&" | "&J15&" | "&K15 -> ELE2609-014 | Electro Independencia | iSoft | WhatsApp masivo
A16: ELE2609-015 | B16: ELE | C16: 2026-09 | D16: Principal | F16: Electro Independencia | G16: 46278 | H16: 46278 | J16: Claro | K16: SMS | L16: Claro SMS | M16: 1600 | N16: GTQ | O16: 0.32 | Q16: =IFERROR(VLOOKUP(K16,Catálogos!$F:$G,2,FALSE()),"Revisar objetivo") -> Por unidad | R16: =A16&" | "&F16&" | "&J16&" | "&K16 -> ELE2609-015 | Electro Independencia | Claro | SMS
A17: ELE2609-016 | B17: ELE | C17: 2026-09 | D17: Principal | F17: Electro Independencia | G17: 46278 | H17: 46282 | I17: 13 y 17 | J17: Mailjet | K17: Mailing | L17: Sin costo | M17: 0 | N17: GTQ | O17: 0 | P17: 4500 | Q17: =IFERROR(VLOOKUP(K17,Catálogos!$F:$G,2,FALSE()),"Revisar objetivo") -> Sin costo | R17: =A17&" | "&F17&" | "&J17&" | "&K17 -> ELE2609-016 | Electro Independencia | Mailjet | Mailing
A18: ELE2609-017 | B18: ELE | C18: 2026-09 | D18: Principal | F18: Electro Days | G18: 46285 | H18: 46291 | J18: Google Ads | K18: Demand Gen · Tráfico | L18: Google | M18: 3000 | N18: GTQ | O18: 0.035 | Q18: =IFERROR(VLOOKUP(K18,Catálogos!$F:$G,2,FALSE()),"Revisar objetivo") -> Por unidad | R18: =A18&" | "&F18&" | "&J18&" | "&K18 -> ELE2609-017 | Electro Days | Google Ads | Demand Gen · Tráfico
A19: ELE2609-018 | B19: ELE | C19: 2026-09 | D19: Principal | F19: Electro Days | G19: 46285 | H19: 46291 | J19: Meta | K19: Tráfico | L19: Meta FB e IG | M19: 2500 | N19: GTQ | O19: 0.2 | Q19: =IFERROR(VLOOKUP(K19,Catálogos!$F:$G,2,FALSE()),"Revisar objetivo") -> Por unidad | R19: =A19&" | "&F19&" | "&J19&" | "&K19 -> ELE2609-018 | Electro Days | Meta | Tráfico
A20: ELE2609-019 | B20: ELE | C20: 2026-09 | D20: Principal | F20: Electro Days | G20: 46285 | H20: 46291 | J20: Meta | K20: Ventas | L20: Meta FB e IG | M20: 2500 | N20: GTQ | O20: 147.06 | Q20: =IFERROR(VLOOKUP(K20,Catálogos!$F:$G,2,FALSE()),"Revisar objetivo") -> Por unidad | R20: =A20&" | "&F20&" | "&J20&" | "&K20 -> ELE2609-019 | Electro Days | Meta | Ventas
A21: ELE2609-020 | B21: ELE | C21: 2026-09 | D21: Principal | F21: Electro Days | G21: 46285 | H21: 46291 | J21: iSoft | K21: WhatsApp masivo | L21: Whatsapp Isoft | M21: 1065 | N21: GTQ | O21: 0.71 | Q21: =IFERROR(VLOOKUP(K21,Catálogos!$F:$G,2,FALSE()),"Revisar objetivo") -> Por unidad | R21: =A21&" | "&F21&" | "&J21&" | "&K21 -> ELE2609-020 | Electro Days | iSoft | WhatsApp masivo
A22: ELE2609-021 | B22: ELE | C22: 2026-09 | D22: Principal | F22: Electro Days | G22: 46285 | H22: 46289 | I22: 20 y 24 | J22: Mailjet | K22: Mailing | L22: Sin costo | M22: 0 | N22: GTQ | O22: 0 | P22: 4500 | Q22: =IFERROR(VLOOKUP(K22,Catálogos!$F:$G,2,FALSE()),"Revisar objetivo") -> Sin costo | R22: =A22&" | "&F22&" | "&J22&" | "&K22 -> ELE2609-021 | Electro Days | Mailjet | Mailing
A23: ELE2609-022 | B23: ELE | C23: 2026-09 | D23: Principal | F23: Talento Humano | G23: 46281 | H23: 46285 | J23: Meta | K23: Tráfico | L23: Extras | M23: 392.5 | N23: GTQ | O23: 0.2355 | Q23: =IFERROR(VLOOKUP(K23,Catálogos!$F:$G,2,FALSE()),"Revisar objetivo") -> Por unidad | R23: =A23&" | "&F23&" | "&J23&" | "&K23 -> ELE2609-022 | Talento Humano | Meta | Tráfico
A24: ELE2608-023 | B24: ELE | C24: 2026-09 | D24: Principal | F24: Leads B2B | G24: 46267 | H24: 46295 | J24: Meta | K24: Lead Forms | L24: Leads B2B | M24: 2000.02 | N24: GTQ | O24: 25 | Q24: =IFERROR(VLOOKUP(K24,Catálogos!$F:$G,2,FALSE()),"Revisar objetivo") -> Por unidad | R24: =A24&" | "&F24&" | "&J24&" | "&K24 -> ELE2608-023 | Leads B2B | Meta | Lead Forms
A25: ELE2609-024 | B25: ELE | C25: 2026-09 | D25: Principal | F25: Capacitación | G25: 46288 | H25: 46294 | J25: Meta | K25: Tráfico | L25: Tráfico a tiendas Geolocalizado | M25: 1000 | N25: GTQ | O25: 0.42 | Q25: =IFERROR(VLOOKUP(K25,Catálogos!$F:$G,2,FALSE()),"Revisar objetivo") -> Por unidad | R25: =A25&" | "&F25&" | "&J25&" | "&K25 -> ELE2609-024 | Capacitación | Meta | Tráfico
A26: ELE2609-025 | B26: ELE | C26: 2026-09 | D26: Principal | F26: Capacitación | G26: 46288 | H26: 46288 | J26: iSoft | K26: WhatsApp masivo | L26: LinkedIn | M26: 1065 | N26: GTQ | O26: 0.71 | Q26: =IFERROR(VLOOKUP(K26,Catálogos!$F:$G,2,FALSE()),"Revisar objetivo") -> Por unidad | R26: =A26&" | "&F26&" | "&J26&" | "&K26 -> ELE2609-025 | Capacitación | iSoft | WhatsApp masivo
A27: ELE2608-002 | B27: ELE | C27: 2026-09 | D27: Arrastre | F27: Mantenimiento | G27: 46266 | H27: 46295 | J27: Meta | K27: Interacción | L27: Meta FB e IG | M27: 0 | N27: GTQ | O27: 0.3 | Q27: =IFERROR(VLOOKUP(K27,Catálogos!$F:$G,2,FALSE()),"Revisar objetivo") -> Por unidad | R27: =A27&" | "&F27&" | "&J27&" | "&K27 -> ELE2608-002 | Mantenimiento | Meta | Interacción

Sheet Catálogos
A1: empresa_codigo | B1: empresa_nombre | C1: medio | D1: medio_fuente | E1: medio_moneda_gasto | F1: objetivo | G1: tipo_costo | H1: actividad | I1: partida | J1: plan | K1: moneda
A2: CGT | B2: Celasa Guatemala | C2: Meta | D2: Porter | E2: USD | F2: Alcance | G2: Por mil | H2: Mantenimiento | I2: Meta FB e IG | J2: Principal | K2: GTQ
A3: CSV | B3: Celasa El Salvador | C3: Google Ads | D3: Porter | E3: USD | F3: Alcance geolocalizado | G3: Por mil | H3: Apoyo CC | I3: Google | J3: Extra | K3: USD
A4: ELE | B4: Electroma | C4: YouTube | D4: Porter | E4: USD | F4: Alcance / Video view | G4: Por mil | H4: Promo CC | I4: YouTube | J4: Arrastre
A5: AME | B5: American | C5: TikTok | D5: Porter | E5: USD | F5: Bumper / Instream | G5: Por mil | H5: Electro Independencia | I5: LinkedIn
A6: LOG | B6: Logistik | C6: LinkedIn | D6: Porter | E6: USD | F6: Display | G6: Por mil | H6: Electro Days | I6: Programatic
C7: Basis | D7: CSV | E7: USD | F7: Display programático | G7: Por mil | H7: Festival de la Iluminación | I7: Claro SMS
C8: Claro | D8: CSV | E8: GTQ | F8: Demand Gen · Alcance | G8: Por mil | H8: Talento Humano | I8: Whatsapp Isoft
C9: iSoft | D9: CSV | E9: GTQ | F9: SMS geolocalizado | G9: Por mil | H9: Envío Insysa | I9: Tik Tok
C10: Mailjet | D10: CSV | E10: GTQ | F10: Interacción | G10: Por unidad | H10: Leads B2B | I10: Leads B2B
F11: Search · Clics | G11: Por unidad | H11: Capacitación | I11: Tráfico a tiendas Geolocalizado
F12: Demand Gen · Tráfico | G12: Por unidad | I12: Mundial
F13: Tráfico | G13: Por unidad | I13: Extras
F14: Mensajes WhatsApp | G14: Por unidad | I14: Sin costo
F15: Ventas | G15: Por unidad
F16: Lead Forms | G16: Por unidad
F17: WhatsApp masivo | G17: Por unidad
F18: SMS | G18: Por unidad
F19: Mailing | G19: Sin costo
A22: Para agregar un medio, objetivo, actividad o partida nueva, agrégalo al final de su columna.
