Workbook

Sheet Léeme
A1: Merkl · Plan de medios estandarizado
A3: Piloto: ELECTROMA · Septiembre 2026. Migrado desde la pestaña '9. Sep' del archivo PRESUPUESTO 2026.
A5: Cómo está organizado
A6: 1. Catálogos: listas fijas de empresas, medios, objetivos, actividades y partidas. Todo el archivo usa estos nombres.
A7: 2. Insights: parámetros del mes, presupuesto por partida, calendario de actividades y KPIs.
A8: 3. Plan: una fila por línea del plan. Es lo que se sube a Merkl.
A9: 4. Control: gasto y resultado reales por línea, con costo real, cumplimiento, pendiente y ritmo diario.
A10: 5. Resumen: por actividad, por partida de presupuesto y por medio.
A11: 6. Revisar: diferencias encontradas al migrar, para confirmar con el equipo.
A13: Reglas
A14: • Celdas amarillas con texto azul = datos que se capturan. Texto negro = fórmulas, no se tocan.
A15: • Cada línea tiene un código único (ELE2609-001). El nombre de campaña en la plataforma debe empezar con ese código.
... A20: • El gasto se captura en la moneda de la plataforma (USD para Meta, Google, YouTube, TikTok, LinkedIn y Basis; Q para Claro, iSoft y Mailjet). Merkl convierte a Q y $.

Sheet Catálogos
A1: Catálogos
A3: Empresa | B3: Código | C3: Moneda del plan | E3: Medio | F3: Plataforma | G3: Moneda del gasto | H3: Fuente de datos | J3: Objetivo | K3: Tipo de costo | L3: Resultado que se mide | N3: Actividad | O3: Tipo | Q3: Partida de presupuesto
A4: Celasa Guatemala | B4: CGT | C4: GTQ | E4: Meta | F4: Meta Ads | G4: USD | H4: Porter | J4: Alcance | K4: Por mil | L4: Personas alcanzadas (únicas) | N4: Mantenimiento | O4: Siempre activa | Q4: Meta FB e IG
A5: Celasa El Salvador | B5: CSV | C5: USD | E5: Google Ads | F5: Google Ads | G5: USD | H5: Porter | J5: Alcance geolocalizado | K5: Por mil | L5: Personas alcanzadas (únicas) | N5: Apoyo CC | O5: Siempre activa | Q5: Google
A6: Electroma | B6: ELE | C6: GTQ | E6: YouTube | F6: Google Ads | G6: USD | H6: Porter | J6: Alcance / Video view | K6: Por mil | L6: Personas alcanzadas (únicas) | N6: Promo CC | O6: Oferta | Q6: YouTube
A7: American | B7: AME | C7: GTQ | E7: TikTok | F7: TikTok Ads | G7: USD | H7: Porter | J7: Bumper / Instream | K7: Por mil | L7: Personas alcanzadas (únicas) | N7: Electro Independencia | O7: Oferta principal | Q7: LinkedIn
A8: Logistik | B8: LOG | C8: GTQ | E8: LinkedIn | F8: LinkedIn Ads | G8: USD | H8: Porter | J8: Display programático | K8: Por mil | L8: Personas alcanzadas (únicas) | N8: Electro Days | O8: Oferta | Q8: Programatic
E9: Basis | F9: Basis | G9: USD | H9: CSV | J9: Demand Gen · Alcance | K9: Por mil | L9: Personas alcanzadas (únicas) | N9: Talento Humano | O9: Extra | Q9: Claro SMS
E10: Claro | F10: Claro | G10: GTQ | H10: CSV | J10: SMS geolocalizado | K10: Por mil | L10: SMS entregados | N10: Leads B2B | O10: B2B | Q10: Whatsapp Isoft
E11: iSoft | F11: iSoft | G11: GTQ | H11: CSV | J11: Interacción | K11: Por unidad | L11: Interacciones | N11: Capacitación | O11: Evento | Q11: Tik Tok
E12: Mailjet | F12: Mailjet | G12: GTQ | H12: CSV | J12: Search · Clics | K12: Por unidad | L12: Clics | Q12: Leads B2B
J13: Demand Gen · Tráfico | K13: Por unidad | L13: Clics | Q13: Tráfico a tiendas Geolocalizado
J14: Tráfico | K14: Por unidad | L14: Clics al sitio | Q14: Mundial
J15: Mensajes WhatsApp | K15: Por unidad | L15: Conversaciones | Q15: Extras
J16: Ventas | K16: Por unidad | L16: Compras | Q16: Sin costo
J17: Lead Forms | K17: Por unidad | L17: Leads
J18: WhatsApp masivo | K18: Por unidad | L18: Mensajes enviados
J19: SMS | K19: Por unidad | L19: SMS enviados
J20: Mailing | K20: Sin costo | L20: Correos enviados

Sheet Insights
A1: Insights · Electroma · Septiembre 2026
A3: Parámetro | B3: Valor
A4: Empresa | B4: Electroma
A5: Código de empresa | B5: ELE
A6: Mes | B6: 2026-09
A7: Tipo de cambio (Q por $) | B7: 7.85
A8: Fecha de corte del control | B8: 46295
A11: Partida de presupuesto | B11: Saldo anterior (Q) | C11: Presupuesto del mes (Q) | D11: Disponible (Q)
A12: Meta FB e IG | B12: 7672.4626 | C12: 23000 | D12: =B12+C12 -> 30672.463
A13: Google | B13: -9351.8145 | C13: 13268.89 | D13: =B13+C13 -> 3917.0755
A14: YouTube | B14: -12879.547 | C14: 3922.22 | D14: =B14+C14 -> -8957.3265
A15: LinkedIn | B15: 7000.6165 | C15: 2000 | D15: =B15+C15 -> 9000.6165
A16: Programatic | B16: -1013.327 | C16: 2285.71 | D16: =B16+C16 -> 1272.383
A17: Claro SMS | B17: -1089.28 | C17: 480 | D17: =B17+C17 -> -609.28
A18: Whatsapp Isoft | B18: -8807.5221 | C18: 5000 | D18: =B18+C18 -> -3807.5221
A19: Tik Tok | B19: 8846.2015 | C19: 3973.33 | D19: =B19+C19 -> 12819.531
A20: Leads B2B | B20: 9566.4587 | C20: 3571.4286 | D20: =B20+C20 -> 13137.887
A21: Tráfico a tiendas Geolocalizado | B21: 3789.3297 | C21: 3571.4286 | D21: =B21+C21 -> 7360.7583
A22: Mundial | B22: -4057.263 | C22: 0 | D22: =B22+C22 -> -4057.263
A23: Extras | B23: 0 | C23: 0 | D23: =B23+C23 -> 0
A24: Total | B24: =SUM(B12:B23) -> -323.68407 | C24: =SUM(C12:C23) -> 61073.007 | D24: =SUM(D12:D23) -> 60749.323
A27: Actividad del calendario | B27: Fecha inicio | C27: Fecha fin
A28: Revelación Electro Independencia | B28: 46275 | C28: 46275
A29: Leads B2B | B29: 46280 | C29: 46295
A30: Electro Independencia | B30: 46281 | C30: 46284
A31: Electro Days | B31: 46285 | C31: 46291
A32: Promo CC | B32: 46286 | C32: 46291
A33: Sale Capacitación | B33: 46288 | C33: 46288
A34: Envío de capacitación | B34: 46294 | C34: 46294
A35: Capacitación | B35: 46294 | C35: 46294
A38: KPI | B38: 2024 | C38: 2025 | D38: Meta 2026 | E38: Crecimiento 2025 vs 2024 | F38: Crecimiento meta vs 2025
A39: Alcance | B39: 5136036 | C39: 8773997 | E39: =IF(B39=0,"",C39/B39-1) -> 0.70832078 | F39: =IF(OR(D39="",C39=0),"",D39/C39-1)
A40: MQLs | B40: 5958 | C40: 15335 | E40: =IF(B40=0,"",C40/B40-1) -> 1.5738503 | F40: =IF(OR(D40="",C40=0),"",D40/C40-1)
A41: Interacción | B41: 215696 | C41: 259094 | E41: =IF(B41=0,"",C41/B41-1) -> 0.20119984 | F41: =IF(OR(D41="",C41=0),"",D41/C41-1)
A42: Usuarios web | B42: 59879 | C42: 96062 | E42: =IF(B42=0,"",C42/B42-1) -> 0.60426861 | F42: =IF(OR(D42="",C42=0),"",D42/C42-1)
A43: La meta 2026 venía vacía en el Excel original: llenarla para que Merkl mida contra ella.

Sheet Plan
A1: Plan de medios · Electroma · Septiembre 2026
A2: Una fila por línea. Amarillo = captura. El tipo de costo, la inversión en $, el proyectado y el nombre de campaña se calculan solos.
A4: Código | B4: Empresa | C4: Mes | D4: Plan | E4: Actividad | F4: Fecha inicio | G4: Fecha fin | H4: Fechas de envío | I4: Medio | J4: Objetivo | K4: Partida de presupuesto | L4: Tipo de costo | M4: Inversión Q | N4: Inversión $ | O4: Costo estimado (Q) | P4: Proyectado manual | Q4: Resultado proyectado | R4: Días | S4: Nombre de campaña
A5: ELE2609-001 | B5: =Insights!$B$4 -> Electroma | C5: =Insights!$B$6 -> 2026-09 | D5: Principal | E5: Mantenimiento | F5: 46266 | G5: 46295 | I5: Meta | J5: Alcance | K5: Meta FB e IG | L5: =IFERROR(VLOOKUP(J5,Catálogos!$J$4:$K$20,2,FALSE()),"Revisar objetivo") -> Por mil | M5: 2000 | N5: =M5/Insights!$B$7 -> 254.77707 | O5: 2.85 | Q5: =IF(OR(L5="Sin costo",O5=0),N(P5),M5/O5*IF(L5="Por mil",1000,1)) -> 701754.39 | R5: =G5-F5+1 -> 30 | S5: =A5&" | "&E5&" | "&I5&" | "&J5 -> ELE2609-001 | Mantenimiento | Meta | Alcance
A6: ELE2609-002 | B6: =Insights!$B$4 -> Electroma | C6: =Insights!$B$6 -> 2026-09 | D6: Principal | E6: Mantenimiento | F6: 46266 | G6: 46295 | I6: Meta | J6: Interacción | K6: Meta FB e IG | L6: =IFERROR(VLOOKUP(J6,Catálogos!$J$4:$K$20,2,FALSE()),"Revisar objetivo") -> Por unidad | M6: 2715 | N6: =M6/Insights!$B$7 -> 345.85987 | O6: 0.3 | Q6: =IF(OR(L6="Sin costo",O6=0),N(P6),M6/O6*IF(L6="Por mil",1000,1)) -> 9050 | R6: =G6-F6+1 -> 30 | S6: =A6&" | "&E6&" | "&I6&" | "&J6 -> ELE2609-002 | Mantenimiento | Meta | Interacción
A7: ELE2608-003 | B7: =Insights!$B$4 -> Electroma | C7: =Insights!$B$6 -> 2026-09 | D7: Principal | E7: Mantenimiento | F7: 46266 | G7: 46295 | I7: Google Ads | J7: Search · Clics | K7: Google | L7: =IFERROR(VLOOKUP(J7,Catálogos!$J$4:$K$20,2,FALSE()),"Revisar objetivo") -> Por unidad | M7: 3500 | N7: =M7/Insights!$B$7 -> 445.85987 | O7: 0.65 | Q7: =IF(OR(L7="Sin costo",O7=0),N(P7),M7/O7*IF(L7="Por mil",1000,1)) -> 5384.6154 | R7: =G7-F7+1 -> 30 | S7: =A7&" | "&E7&" | "&I7&" | "&J7 -> ELE2608-003 | Mantenimiento | Google Ads | Search · Clics
A8: ELE2609-004 | B8: =Insights!$B$4 -> Electroma | C8: =Insights!$B$6 -> 2026-09 | D8: Principal | E8: Mantenimiento | F8: 46266 | G8: 46295 | I8: TikTok | J8: Alcance | K8: Tik Tok | L8: =IFERROR(VLOOKUP(J8,Catálogos!$J$4:$K$20,2,FALSE()),"Revisar objetivo") -> Por mil | M8: 2000 | N8: =M8/Insights!$B$7 -> 254.77707 | O8: 2.4 | Q8: =IF(OR(L8="Sin costo",O8=0),N(P8),M8/O8*IF(L8="Por mil",1000,1)) -> 833333.33 | R8: =G8-F8+1 -> 30 | S8: =A8&" | "&E8&" | "&I8&" | "&J8 -> ELE2609-004 | Mantenimiento | TikTok | Alcance
A9: ELE2608-006 | B9: =Insights!$B$4 -> Electroma | C9: =Insights!$B$6 -> 2026-09 | D9: Principal | E9: Apoyo CC | F9: 46266 | G9: 46295 | I9: Meta | J9: Mensajes WhatsApp | K9: Meta FB e IG | L9: =IFERROR(VLOOKUP(J9,Catálogos!$J$4:$K$20,2,FALSE()),"Revisar objetivo") -> Por unidad | M9: 3500 | N9: =M9/Insights!$B$7 -> 445.85987 | O9: 2.4 | Q9: =IF(OR(L9="Sin costo",O9=0),N(P9),M9/O9*IF(L9="Por mil",1000,1)) -> 1458.3333 | R9: =G9-F9+1 -> 30 | S9: =A9&" | "&E9&" | "&I9&" | "&J9 -> ELE2608-006 | Apoyo CC | Meta | Mensajes WhatsApp
A10: ELE2609-006 | B10: =Insights!$B$4 -> Electroma | C10: =Insights!$B$6 -> 2026-09 | D10: Principal | E10: Promo CC | F10: 46286 | G10: 46291 | I10: Meta | J10: Mensajes WhatsApp | K10: Meta FB e IG | L10: =IFERROR(VLOOKUP(J10,Catálogos!$J$4:$K$20,2,FALSE()),"Revisar objetivo") -> Por unidad | M10: 2000.023 | N10: =M10/Insights!$B$7 -> 254.78 | O10: 4 | Q10: =IF(OR(L10="Sin costo",O10=0),N(P10),M10/O10*IF(L10="Por mil",1000,1)) -> 500.00575 | R10: =G10-F10+1 -> 6 | S10: =A10&" | "&E10&" | "&I10&" | "&J10 -> ELE2609-006 | Promo CC | Meta | Mensajes WhatsApp
A11: ELE2609-007 | B11: =Insights!$B$4 -> Electroma | C11: =Insights!$B$6 -> 2026-09 | D11: Principal | E11: Electro Independencia | F11: 46275 | G11: 46284 | I11: Meta | J11: Alcance geolocalizado | K11: Meta FB e IG | L11: =IFERROR(VLOOKUP(J11,Catálogos!$J$4:$K$20,2,FALSE()),"Revisar objetivo") -> Por mil | M11: 12000 | N11: =M11/Insights!$B$7 -> 1528.6624 | O11: 3.9 | Q11: =IF(OR(L11="Sin costo",O11=0),N(P11),M11/O11*IF(L11="Por mil",1000,1)) -> 3076923.1 | R11: =G11-F11+1 -> 10 | S11: =A11&" | "&E11&" | "&I11&" | "&J11 -> ELE2609-007 | Electro Independencia | Meta | Alcance geolocalizado
A12: ELE2609-008 | B12: =Insights!$B$4 -> Electroma | C12: =Insights!$B$6 -> 2026-09 | D12: Principal | E12: Electro Independencia | F12: 46278 | G12: 46284 | I12: TikTok | J12: Alcance / Video view | K12: Tik Tok | L12: =IFERROR(VLOOKUP(J12,Catálogos!$J$4:$K$20,2,FALSE()),"Revisar objetivo") -> Por mil | M12: 6454.18 | N12: =M12/Insights!$B$7 -> 822.18854 | O12: 2.4 | Q12: =IF(OR(L12="Sin costo",O12=0),N(P12),M12/O12*IF(L12="Por mil",1000,1)) -> 2689241.7 | R12: =G12-F12+1 -> 7 | S12: =A12&" | "&E12&" | "&I12&" | "&J12 -> ELE2609-008 | Electro Independencia | TikTok | Alcance / Video view
A13: ELE2609-009 | B13: =Insights!$B$4 -> Electroma | C13: =Insights!$B$6 -> 2026-09 | D13: Principal | E13: Electro Independencia | F13: 46278 | G13: 46284 | I13: YouTube | J13: Bumper / Instream | K13: YouTube | L13: =IFERROR(VLOOKUP(J13,Catálogos!$J$4:$K$20,2,FALSE()),"Revisar objetivo") -> Por mil | M13: 5000 | N13: =M13/Insights!$B$7 -> 636.94268 | O13: 3.5 | Q13: =IF(OR(L13="Sin costo",O13=0),N(P13),M13/O13*IF(L13="Por mil",1000,1)) -> 1428571.4 | R13: =G13-F13+1 -> 7 | S13: =A13&" | "&E13&" | "&I13&" | "&J13 -> ELE2609-009 | Electro Independencia | YouTube | Bumper / Instream
A14: ELE2609-010 | B14: =Insights!$B$4 -> Electroma | C14: =Insights!$B$6 -> 2026-09 | D14: Principal | E14: Electro Independencia | F14: 46278 | G14: 46284 | I14: Basis | J14: Display programático | K14: Programatic | L14: =IFERROR(VLOOKUP(J14,Catálogos!$J$4:$K$20,2,FALSE()),"Revisar objetivo") -> Por mil | M14: 4300 | N14: =M14/Insights!$B$7 -> 547.7707 | O14: 6.19 | Q14: =IF(OR(L14="Sin costo",O14=0),N(P14),M14/O14*IF(L14="Por mil",1000,1)) -> 694668.82 | R14: =G14-F14+1 -> 7 | S14: =A14&" | "&E14&" | "&I14&" | "&J14 -> ELE2609-010 | Electro Independencia | Basis | Display programático
A15: ELE2609-011 | B15: =Insights!$B$4 -> Electroma | C15: =Insights!$B$6 -> 2026-09 | D15: Principal | E15: Electro Independencia | F15: 46278 | G15: 46284 | I15: Google Ads | J15: Demand Gen · Alcance | K15: Google | L15: =IFERROR(VLOOKUP(J15,Catálogos!$J$4:$K$20,2,FALSE()),"Revisar objetivo") -> Por mil | M15: 2756.61 | N15: =M15/Insights!$B$7 -> 351.16051 | O15: 7.82 | Q15: =IF(OR(L15="Sin costo",O15=0),N(P15),M15/O15*IF(L15="Por mil",1000,1)) -> 352507.67 | R15: =G15-F15+1 -> 7 | S15: =A15&" | "&E15&" | "&I15&" | "&J15 -> ELE2609-011 | Electro Independencia | Google Ads | Demand Gen · Alcance
A16: ELE2609-012 | B16: =Insights!$B$4 -> Electroma | C16: =Insights!$B$6 -> 2026-09 | D16: Principal | E16: Electro Independencia | F16: 46280 | G16: 46280 | I16: Claro | J16: SMS geolocalizado | K16: Programatic | L16: =IFERROR(VLOOKUP(J16,Catálogos!$J$4:$K$20,2,FALSE()),"Revisar objetivo") -> Por mil | M16: 1000 | N16: =M16/Insights!$B$7 -> 127.38854 | O16: 77 | Q16: =IF(OR(L16="Sin costo",O16=0),N(P16),M16/O16*IF(L16="Por mil",1000,1)) -> 12987.013 | R16: =G16-F16+1 -> 1 | S16: =A16&" | "&E16&" | "&I16&" | "&J16 -> ELE2609-012 | Electro Independencia | Claro | SMS geolocalizado
A17: ELE2609-013 | B17: =Insights!$B$4 -> Electroma | C17: =Insights!$B$6 -> 2026-09 | D17: Principal | E17: Electro Independencia | F17: 46282 | G17: 46282 | I17: Claro | J17: SMS geolocalizado | K17: Programatic | L17: =IFERROR(VLOOKUP(J17,Catálogos!$J$4:$K$20,2,FALSE()),"Revisar objetivo") -> Por mil | M17: 1000 | N17: =M17/Insights!$B$7 -> 127.38854 | O17: 77 | Q17: =IF(OR(L17="Sin costo",O17=0),N(P17),M17/O17*IF(L17="Por mil",1000,1)) -> 12987.013 | R17: =G17-F17+1 -> 1 | S17: =A17&" | "&E17&" | "&I17&" | "&J17 -> ELE2609-013 | Electro Independencia | Claro | SMS geolocalizado
A18: ELE2609-014 | B18: =Insights!$B$4 -> Electroma | C18: =Insights!$B$6 -> 2026-09 | D18: Principal | E18: Electro Independencia | F18: 46278 | G18: 46282 | H18: 13 y 17 | I18: iSoft | J18: WhatsApp masivo | K18: Whatsapp Isoft | L18: =IFERROR(VLOOKUP(J18,Catálogos!$J$4:$K$20,2,FALSE()),"Revisar objetivo") -> Por unidad | M18: 2800 | N18: =M18/Insights!$B$7 -> 356.6879 | O18: 0.71 | Q18: =IF(OR(L18="Sin costo",O18=0),N(P18),M18/O18*IF(L18="Por mil",1000,1)) -> 3943.662 | R18: =G18-F18+1 -> 5 | S18: =A18&" | "&E18&" | "&I18&" | "&J18 -> ELE2609-014 | Electro Independencia | iSoft | WhatsApp masivo
A19: ELE2609-015 | B19: =Insights!$B$4 -> Electroma | C19: =Insights!$B$6 -> 2026-09 | D19: Principal | E19: Electro Independencia | F19: 46278 | G19: 46278 | I19: Claro | J19: SMS | K19: Claro SMS | L19: =IFERROR(VLOOKUP(J19,Catálogos!$J$4:$K$20,2,FALSE()),"Revisar objetivo") -> Por unidad | M19: 1600 | N19: =M19/Insights!$B$7 -> 203.82166 | O19: 0.32 | Q19: =IF(OR(L19="Sin costo",O19=0),N(P19),M19/O19*IF(L19="Por mil",1000,1)) -> 5000 | R19: =G19-F19+1 -> 1 | S19: =A19&" | "&E19&" | "&I19&" | "&J19 -> ELE2609-015 | Electro Independencia | Claro | SMS
A20: ELE2609-016 | B20: =Insights!$B$4 -> Electroma | C20: =Insights!$B$6 -> 2026-09 | D20: Principal | E20: Electro Independencia | F20: 46278 | G20: 46282 | H20: 13 y 17 | I20: Mailjet | J20: Mailing | K20: Sin costo | L20: =IFERROR(VLOOKUP(J20,Catálogos!$J$4:$K$20,2,FALSE()),"Revisar objetivo") -> Sin costo | M20: 0 | N20: =M20/Insights!$B$7 -> 0 | O20: 0 | P20: 4500 | Q20: =IF(OR(L20="Sin costo",O20=0),N(P20),M20/O20*IF(L20="Por mil",1000,1)) -> 4500 | R20: =G20-F20+1 -> 5 | S20: =A20&" | "&E20&" | "&I20&" | "&J20 -> ELE2609-016 | Electro Independencia | Mailjet | Mailing
A21: ELE2609-017 | B21: =Insights!$B$4 -> Electroma | C21: =Insights!$B$6 -> 2026-09 | D21: Principal | E21: Electro Days | F21: 46285 | G21: 46291 | I21: Google Ads | J21: Demand Gen · Tráfico | K21: Google | L21: =IFERROR(VLOOKUP(J21,Catálogos!$J$4:$K$20,2,FALSE()),"Revisar objetivo") -> Por unidad | M21: 3000 | N21: =M21/Insights!$B$7 -> 382.16561 | O21: 0.035 | Q21: =IF(OR(L21="Sin costo",O21=0),N(P21),M21/O21*IF(L21="Por mil",1000,1)) -> 85714.286 | R21: =G21-F21+1 -> 7 | S21: =A21&" | "&E21&" | "&I21&" | "&J21 -> ELE2609-017 | Electro Days | Google Ads | Demand Gen · Tráfico
A22: ELE2609-018 | B22: =Insights!$B$4 -> Electroma | C22: =Insights!$B$6 -> 2026-09 | D22: Principal | E22: Electro Days | F22: 46285 | G22: 46291 | I22: Meta | J22: Tráfico | K22: Meta FB e IG | L22: =IFERROR(VLOOKUP(J22,Catálogos!$J$4:$K$20,2,FALSE()),"Revisar objetivo") -> Por unidad | M22: 2500 | N22: =M22/Insights!$B$7 -> 318.47134 | O22: 0.2 | Q22: =IF(OR(L22="Sin costo",O22=0),N(P22),M22/O22*IF(L22="Por mil",1000,1)) -> 12500 | R22: =G22-F22+1 -> 7 | S22: =A22&" | "&E22&" | "&I22&" | "&J22 -> ELE2609-018 | Electro Days | Meta | Tráfico
A23: ELE2609-019 | B23: =Insights!$B$4 -> Electroma | C23: =Insights!$B$6 -> 2026-09 | D23: Principal | E23: Electro Days | F23: 46285 | G23: 46291 | I23: Meta | J23: Ventas | K23: Meta FB e IG | L23: =IFERROR(VLOOKUP(J23,Catálogos!$J$4:$K$20,2,FALSE()),"Revisar objetivo") -> Por unidad | M23: 2500 | N23: =M23/Insights!$B$7 -> 318.47134 | O23: 147.06 | Q23: =IF(OR(L23="Sin costo",O23=0),N(P23),M23/O23*IF(L23="Por mil",1000,1)) -> 16.999864 | R23: =G23-F23+1 -> 7 | S23: =A23&" | "&E23&" | "&I23&" | "&J23 -> ELE2609-019 | Electro Days | Meta | Ventas
A24: ELE2609-020 | B24: =Insights!$B$4 -> Electroma | C24: =Insights!$B$6 -> 2026-09 | D24: Principal | E24: Electro Days | F24: 46285 | G24: 46291 | I24: iSoft | J24: WhatsApp masivo | K24: Whatsapp Isoft | L24: =IFERROR(VLOOKUP(J24,Catálogos!$J$4:$K$20,2,FALSE()),"Revisar objetivo") -> Por unidad | M24: 1065 | N24: =M24/Insights!$B$7 -> 135.66879 | O24: 0.71 | Q24: =IF(OR(L24="Sin costo",O24=0),N(P24),M24/O24*IF(L24="Por mil",1000,1)) -> 1500 | R24: =G24-F24+1 -> 7 | S24: =A24&" | "&E24&" | "&I24&" | "&J24 -> ELE2609-020 | Electro Days | iSoft | WhatsApp masivo
A25: ELE2609-021 | B25: =Insights!$B$4 -> Electroma | C25: =Insights!$B$6 -> 2026-09 | D25: Principal | E25: Electro Days | F25: 46285 | G25: 46289 | H25: 20 y 24 | I25: Mailjet | J25: Mailing | K25: Sin costo | L25: =IFERROR(VLOOKUP(J25,Catálogos!$J$4:$K$20,2,FALSE()),"Revisar objetivo") -> Sin costo | M25: 0 | N25: =M25/Insights!$B$7 -> 0 | O25: 0 | P25: 4500 | Q25: =IF(OR(L25="Sin costo",O25=0),N(P25),M25/O25*IF(L25="Por mil",1000,1)) -> 4500 | R25: =G25-F25+1 -> 5 | S25: =A25&" | "&E25&" | "&I25&" | "&J25 -> ELE2609-021 | Electro Days | Mailjet | Mailing
A26: ELE2609-022 | B26: =Insights!$B$4 -> Electroma | C26: =Insights!$B$6 -> 2026-09 | D26: Principal | E26: Talento Humano | F26: 46281 | G26: 46285 | I26: Meta | J26: Tráfico | K26: Extras | L26: =IFERROR(VLOOKUP(J26,Catálogos!$J$4:$K$20,2,FALSE()),"Revisar objetivo") -> Por unidad | M26: 392.5 | N26: =M26/Insights!$B$7 -> 50 | O26: 0.2355 | Q26: =IF(OR(L26="Sin costo",O26=0),N(P26),M26/O26*IF(L26="Por mil",1000,1)) -> 1666.6667 | R26: =G26-F26+1 -> 5 | S26: =A26&" | "&E26&" | "&I26&" | "&J26 -> ELE2609-022 | Talento Humano | Meta | Tráfico
A27: ELE2608-023 | B27: =Insights!$B$4 -> Electroma | C27: =Insights!$B$6 -> 2026-09 | D27: Principal | E27: Leads B2B | F27: 46267 | G27: 46295 | I27: Meta | J27: Lead Forms | K27: Leads B2B | L27: =IFERROR(VLOOKUP(J27,Catálogos!$J$4:$K$20,2,FALSE()),"Revisar objetivo") -> Por unidad | M27: 2000.023 | N27: =M27/Insights!$B$7 -> 254.78 | O27: 25 | Q27: =IF(OR(L27="Sin costo",O27=0),N(P27),M27/O27*IF(L27="Por mil",1000,1)) -> 80.00092 | R27: =G27-F27+1 -> 29 | S27: =A27&" | "&E27&" | "&I27&" | "&J27 -> ELE2608-023 | Leads B2B | Meta | Lead Forms
A28: ELE2609-024 | B28: =Insights!$B$4 -> Electroma | C28: =Insights!$B$6 -> 2026-09 | D28: Principal | E28: Capacitación | F28: 46288 | G28: 46294 | I28: Meta | J28: Tráfico | K28: Tráfico a tiendas Geolocalizado | L28: =IFERROR(VLOOKUP(J28,Catálogos!$J$4:$K$20,2,FALSE()),"Revisar objetivo") -> Por unidad | M28: 1000 | N28: =M28/Insights!$B$7 -> 127.38854 | O28: 0.42 | Q28: =IF(OR(L28="Sin costo",O28=0),N(P28),M28/O28*IF(L28="Por mil",1000,1)) -> 2380.9524 | R28: =G28-F28+1 -> 7 | S28: =A28&" | "&E28&" | "&I28&" | "&J28 -> ELE2609-024 | Capacitación | Meta | Tráfico
A29: ELE2609-025 | B29: =Insights!$B$4 -> Electroma | C29: =Insights!$B$6 -> 2026-09 | D29: Principal | E29: Capacitación | F29: 46288 | G29: 46288 | I29: iSoft | J29: WhatsApp masivo | K29: LinkedIn | L29: =IFERROR(VLOOKUP(J29,Catálogos!$J$4:$K$20,2,FALSE()),"Revisar objetivo") -> Por unidad | M29: 1065 | N29: =M29/Insights!$B$7 -> 135.66879 | O29: 0.71 | Q29: =IF(OR(L29="Sin costo",O29=0),N(P29),M29/O29*IF(L29="Por mil",1000,1)) -> 1500 | R29: =G29-F29+1 -> 1 | S29: =A29&" | "&E29&" | "&I29&" | "&J29 -> ELE2609-025 | Capacitación | iSoft | WhatsApp masivo
A30: ELE2608-002 | B30: =Insights!$B$4 -> Electroma | C30: =Insights!$B$6 -> 2026-09 | D30: Arrastre | E30: Mantenimiento | F30: 46266 | G30: 46295 | I30: Meta | J30: Interacción | K30: Meta FB e IG | L30: =IFERROR(VLOOKUP(J30,Catálogos!$J$4:$K$20,2,FALSE()),"Revisar objetivo") -> Por unidad | M30: 0 | N30: =M30/Insights!$B$7 -> 0 | O30: 0.3 | Q30: =IF(OR(L30="Sin costo",O30=0),N(P30),M30/O30*IF(L30="Por mil",1000,1)) -> 0 | R30: =G30-F30+1 -> 30 | S30: =A30&" | "&E30&" | "&I30&" | "&J30 -> ELE2608-002 | Mantenimiento | Meta | Interacción
A31: Total | M31: =SUM(M5:M30) -> 66148.336 | N31: =SUM(N5:N30) -> 8426.5396
A33: Total del plan en el Excel original: Q65,694.13. Aquí suma Q454.21 más por la corrección confirmada de ELE2609-011 (Q2,756.61).

Sheet Control
A1: Control de campañas · Electroma · Septiembre 2026
A2: Captura el gasto en la moneda de la plataforma y el resultado. En Merkl estas dos columnas llegarán solas desde Porter o desde el CSV.
A4: Código | B4: Actividad | C4: Medio | D4: Objetivo | E4: Partida | F4: Moneda del gasto | G4: Gastado en plataforma | H4: Resultado | I4: Inversión Q | J4: Gastado Q | K4: Gastado $ | L4: Proyectado | M4: Costo estimado | N4: Costo real | O4: Cumplimiento | P4: Pendiente Q | Q4: Pendiente $ | R4: Opt. costo | S4: Días transcurridos | T4: Gasto diario plan | U4: Gasto diario real | V4: Resultado diario plan | W4: Resultado diario real | X4: Estado
A5: =Plan!A5 -> ELE2609-001 | B5: =Plan!E5 -> Mantenimiento | C5: =Plan!I5 -> Meta | D5: =Plan!J5 -> Alcance | E5: =Plan!K5 -> Meta FB e IG | F5: =IFERROR(VLOOKUP(C5,Catálogos!$E$4:$G$12,3,FALSE()),"Revisar medio") -> USD | G5: 254.36 | H5: 596165 | I5: =Plan!M5 -> 2000 | J5: =IF(F5="USD",G5*Insights!$B$7,G5) -> 1996.726 | K5: =J5/Insights!$B$7 -> 254.36 | L5: =Plan!Q5 -> 701754.39 | M5: =Plan!O5 -> 2.85 | N5: =IF(OR(H5=0,Plan!L5="Sin costo"),"",J5/H5*IF(Plan!L5="Por mil",1000,1)) -> 3.3492842 | O5: =IF(L5=0,"",H5/L5) -> 0.84953512 | P5: =I5-J5 -> 3.274 | Q5: =P5/Insights!$B$7 -> 0.41707006 | R5: =IF(OR(M5=0,N5=""),"",N5/M5) -> 1.1751874 | S5: =MAX(0,MIN(Insights!$B$8,Plan!G5)-Plan!F5+1) -> 30 | T5: =I5/Plan!R5 -> 66.666667 | U5: =IF(S5=0,"",J5/S5) -> 66.557533 | V5: =L5/Plan!R5 -> 23391.813 | W5: =IF(S5=0,"",H5/S5) -> 19872.167 | X5: =IF(S5=0,"Sin iniciar",IF(J5>I5*1.05,"Gastó de más",IF(AND(O5<>"",O5<0.8),"Bajo proyección",IF(AND(R5<>"",R5>1.2),"Costo alto","En línea")))) -> En línea
A6: =Plan!A6 -> ELE2609-002 | B6: =Plan!E6 -> Mantenimiento | C6: =Plan!I6 -> Meta | D6: =Plan!J6 -> Interacción | E6: =Plan!K6 -> Meta FB e IG | F6: =IFERROR(VLOOKUP(C6,Catálogos!$E$4:$G$12,3,FALSE()),"Revisar medio") -> USD | G6: 335.65 | H6: 16356 | I6: =Plan!M6 -> 2715 | J6: =IF(F6="USD",G6*Insights!$B$7,G6) -> 2634.8525 | K6: =J6/Insights!$B$7 -> 335.65 | L6: =Plan!Q6 -> 9050 | M6: =Plan!O6 -> 0.3 | N6: =IF(OR(H6=0,Plan!L6="Sin costo"),"",J6/H6*IF(Plan!L6="Por mil",1000,1)) -> 0.16109394 | O6: =IF(L6=0,"",H6/L6) -> 1.8072928 | P6: =I6-J6 -> 80.1475 | Q6: =P6/Insights!$B$7 -> 10.209873 | R6: =IF(OR(M6=0,N6=""),"",N6/M6) -> 0.5369798 | S6: =MAX(0,MIN(Insights!$B$8,Plan!G6)-Plan!F6+1) -> 30 | T6: =I6/Plan!R6 -> 90.5 | U6: =IF(S6=0,"",J6/S6) -> 87.828417 | V6: =L6/Plan!R6 -> 301.66667 | W6: =IF(S6=0,"",H6/S6) -> 545.2 | X6: =IF(S6=0,"Sin iniciar",IF(J6>I6*1.05,"Gastó de más",IF(AND(O6<>"",O6<0.8),"Bajo proyección",IF(AND(R6<>"",R6>1.2),"Costo alto","En línea")))) -> En línea
A7: =Plan!A7 -> ELE2608-003 | B7: =Plan!E7 -> Mantenimiento | C7: =Plan!I7 -> Google Ads | D7: =Plan!J7 -> Search · Clics | E7: =Plan!K7 -> Google | F7: =IFERROR(VLOOKUP(C7,Catálogos!$E$4:$G$12,3,FALSE()),"Revisar medio") -> USD | G7: 463.13 | H7: 7500 | I7: =Plan!M7 -> 3500 | J7: =IF(F7="USD",G7*Insights!$B$7,G7) -> 3635.5705 | K7: =J7/Insights!$B$7 -> 463.13 | L7: =Plan!Q7 -> 5384.6154 | M7: =Plan!O7 -> 0.65 | N7: =IF(OR(H7=0,Plan!L7="Sin costo"),"",J7/H7*IF(Plan!L7="Por mil",1000,1)) -> 0.48474273 | O7: =IF(L7=0,"",H7/L7) -> 1.3928571 | P7: =I7-J7 -> -135.5705 | Q7: =P7/Insights!$B$7 -> -17.270127 | R7: =IF(OR(M7=0,N7=""),"",N7/M7) -> 0.74575805 | S7: =MAX(0,MIN(Insights!$B$8,Plan!G7)-Plan!F7+1) -> 30 | T7: =I7/Plan!R7 -> 116.66667 | U7: =IF(S7=0,"",J7/S7) -> 121.18568 | V7: =L7/Plan!R7 -> 179.48718 | W7: =IF(S7=0,"",H7/S7) -> 250 | X7: =IF(S7=0,"Sin iniciar",IF(J7>I7*1.05,"Gastó de más",IF(AND(O7<>"",O7<0.8),"Bajo proyección",IF(AND(R7<>"",R7>1.2),"Costo alto","En línea")))) -> En línea
A8: =Plan!A8 -> ELE2609-004 | B8: =Plan!E8 -> Mantenimiento | C8: =Plan!I8 -> TikTok | D8: =Plan!J8 -> Alcance | E8: =Plan!K8 -> Tik Tok | F8: =IFERROR(VLOOKUP(C8,Catálogos!$E$4:$G$12,3,FALSE()),"Revisar medio") -> USD | G8: 91.26 | H8: 408324 | I8: =Plan!M8 -> 2000 | J8: =IF(F8="USD",G8*Insights!$B$7,G8) -> 716.391 | K8: =J8/Insights!$B$7 -> 91.26 | L8: =Plan!Q8 -> 833333.33 | M8: =Plan!O8 -> 2.4 | N8: =IF(OR(H8=0,Plan!L8="Sin costo"),"",J8/H8*IF(Plan!L8="Por mil",1000,1)) -> 1.754467 | O8: =IF(L8=0,"",H8/L8) -> 0.4899888 | P8: =I8-J8 -> 1283.609 | Q8: =P8/Insights!$B$7 -> 163.51707 | R8: =IF(OR(M8=0,N8=""),"",N8/M8) -> 0.73102793 | S8: =MAX(0,MIN(Insights!$B$8,Plan!G8)-Plan!F8+1) -> 30 | T8: =I8/Plan!R8 -> 66.666667 | U8: =IF(S8=0,"",J8/S8) -> 23.8797 | V8: =L8/Plan!R8 -> 27777.778 | W8: =IF(S8=0,"",H8/S8) -> 13610.8 | X8: =IF(S8=0,"Sin iniciar",IF(J8>I8*1.05,"Gastó de más",IF(AND(O8<>"",O8<0.8),"Bajo proyección",IF(AND(R8<>"",R8>1.2),"Costo alto","En línea")))) -> Bajo proyección
A9: =Plan!A9 -> ELE2608-006 | B9: =Plan!E9 -> Apoyo CC | C9: =Plan!I9 -> Meta | D9: =Plan!J9 -> Mensajes WhatsApp | E9: =Plan!K9 -> Meta FB e IG | F9: =IFERROR(VLOOKUP(C9,Catálogos!$E$4:$G$12,3,FALSE()),"Revisar medio") -> USD | G9: 445.42 | H9: 1480 | I9: =Plan!M9 -> 3500 | J9: =IF(F9="USD",G9*Insights!$B$7,G9) -> 3496.547 | K9: =J9/Insights!$B$7 -> 445.42 | L9: =Plan!Q9 -> 1458.3333 | M9: =Plan!O9 -> 2.4 | N9: =IF(OR(H9=0,Plan!L9="Sin costo"),"",J9/H9*IF(Plan!L9="Por mil",1000,1)) -> 2.3625318 | O9: =IF(L9=0,"",H9/L9) -> 1.0148571 | P9: =I9-J9 -> 3.453 | Q9: =P9/Insights!$B$7 -> 0.43987261 | R9: =IF(OR(M9=0,N9=""),"",N9/M9) -> 0.98438823 | S9: =MAX(0,MIN(Insights!$B$8,Plan!G9)-Plan!F9+1) -> 30 | T9: =I9/Plan!R9 -> 116.66667 | U9: =IF(S9=0,"",J9/S9) -> 116.55157 | V9: =L9/Plan!R9 -> 48.611111 | W9: =IF(S9=0,"",H9/S9) -> 49.333333 | X9: =IF(S9=0,"Sin iniciar",IF(J9>I9*1.05,"Gastó de más",IF(AND(O9<>"",O9<0.8),"Bajo proyección",IF(AND(R9<>"",R9>1.2),"Costo alto","En línea")))) -> En línea
A10: =Plan!A10 -> ELE2609-006 | B10: =Plan!E10 -> Promo CC | C10: =Plan!I10 -> Meta | D10: =Plan!J10 -> Mensajes WhatsApp | E10: =Plan!K10 -> Meta FB e IG | F10: =IFERROR(VLOOKUP(C10,Catálogos!$E$4:$G$12,3,FALSE()),"Revisar medio") -> USD | G10: 254.75 | H10: 548 | I10: =Plan!M10 -> 2000.023 | J10: =IF(F10="USD",G10*Insights!$B$7,G10) -> 1999.7875 | K10: =J10/Insights!$B$7 -> 254.75 | L10: =Plan!Q10 -> 500.00575 | M10: =Plan!O10 -> 4 | N10: =IF(OR(H10=0,Plan!L10="Sin costo"),"",J10/H10*IF(Plan!L10="Por mil",1000,1)) -> 3.6492473 | O10: =IF(L10=0,"",H10/L10) -> 1.0959874 | P10: =I10-J10 -> 0.2355 | Q10: =P10/Insights!$B$7 -> 0.03 | R10: =IF(OR(M10=0,N10=""),"",N10/M10) -> 0.91231182 | S10: =MAX(0,MIN(Insights!$B$8,Plan!G10)-Plan!F10+1) -> 6 | T10: =I10/Plan!R10 -> 333.33717 | U10: =IF(S10=0,"",J10/S10) -> 333.29792 | V10: =L10/Plan!R10 -> 83.334292 | W10: =IF(S10=0,"",H10/S10) -> 91.333333 | X10: =IF(S10=0,"Sin iniciar",IF(J10>I10*1.05,"Gastó de más",IF(AND(O10<>"",O10<0.8),"Bajo proyección",IF(AND(R10<>"",R10>1.2),"Costo alto","En línea")))) -> En línea
A11: =Plan!A11 -> ELE2609-007 | B11: =Plan!E11 -> Electro Independencia | C11: =Plan!I11 -> Meta | D11: =Plan!J11 -> Alcance geolocalizado | E11: =Plan!K11 -> Meta FB e IG | F11: =IFERROR(VLOOKUP(C11,Catálogos!$E$4:$G$12,3,FALSE()),"Revisar medio") -> USD | G11: 1528.66 | H11: 3088427 | I11: =Plan!M11 -> 12000 | J11: =IF(F11="USD",G11*Insights!$B$7,G11) -> 11999.981 | K11: =J11/Insights!$B$7 -> 1528.66 | L11: =Plan!Q11 -> 3076923.1 | M11: =Plan!O11 -> 3.9 | N11: =IF(OR(H11=0,Plan!L11="Sin costo"),"",J11/H11*IF(Plan!L11="Por mil",1000,1)) -> 3.8854669 | O11: =IF(L11=0,"",H11/L11) -> 1.0037388 | P11: =I11-J11 -> 0.019 | Q11: =P11/Insights!$B$7 -> 0.0024203822 | R11: =IF(OR(M11=0,N11=""),"",N11/M11) -> 0.99627357 | S11: =MAX(0,MIN(Insights!$B$8,Plan!G11)-Plan!F11+1) -> 10 | T11: =I11/Plan!R11 -> 1200 | U11: =IF(S11=0,"",J11/S11) -> 1199.9981 | V11: =L11/Plan!R11 -> 307692.31 | W11: =IF(S11=0,"",H11/S11) -> 308842.7 | X11: =IF(S11=0,"Sin iniciar",IF(J11>I11*1.05,"Gastó de más",IF(AND(O11<>"",O11<0.8),"Bajo proyección",IF(AND(R11<>"",R11>1.2),"Costo alto","En línea")))) -> En línea
A12: =Plan!A12 -> ELE2609-008 | B12: =Plan!E12 -> Electro Independencia | C12: =Plan!I12 -> TikTok | D12: =Plan!J12 -> Alcance / Video view | E12: =Plan!K12 -> Tik Tok | F12: =IFERROR(VLOOKUP(C12,Catálogos!$E$4:$G$12,3,FALSE()),"Revisar medio") -> USD | G12: 652.79 | H12: 1928940 | I12: =Plan!M12 -> 6454.18 | J12: =IF(F12="USD",G12*Insights!$B$7,G12) -> 5124.4015 | K12: =J12/Insights!$B$7 -> 652.79 | L12: =Plan!Q12 -> 2689241.7 | M12: =Plan!O12 -> 2.4 | N12: =IF(OR(H12=0,Plan!L12="Sin costo"),"",J12/H12*IF(Plan!L12="Por mil",1000,1)) -> 2.6565894 | O12: =IF(L12=0,"",H12/L12) -> 0.71728027 | P12: =I12-J12 -> 1329.7785 | Q12: =P12/Insights!$B$7 -> 169.39854 | R12: =IF(OR(M12=0,N12=""),"",N12/M12) -> 1.1069122 | S12: =MAX(0,MIN(Insights!$B$8,Plan!G12)-Plan!F12+1) -> 7 | T12: =I12/Plan!R12 -> 922.02571 | U12: =IF(S12=0,"",J12/S12) -> 732.05736 | V12: =L12/Plan!R12 -> 384177.38 | W12: =IF(S12=0,"",H12/S12) -> 275562.86 | X12: =IF(S12=0,"Sin iniciar",IF(J12>I12*1.05,"Gastó de más",IF(AND(O12<>"",O12<0.8),"Bajo proyección",IF(AND(R12<>"",R12>1.2),"Costo alto","En línea")))) -> Bajo proyección
A13: =Plan!A13 -> ELE2609-009 | B13: =Plan!E13 -> Electro Independencia | C13: =Plan!I13 -> YouTube | D13: =Plan!J13 -> Bumper / Instream | E13: =Plan!K13 -> YouTube | F13: =IFERROR(VLOOKUP(C13,Catálogos!$E$4:$G$12,3,FALSE()),"Revisar medio") -> USD | G13: 635.75 | H13: 1177764 | I13: =Plan!M13 -> 5000 | J13: =IF(F13="USD",G13*Insights!$B$7,G13) -> 4990.6375 | K13: =J13/Insights!$B$7 -> 635.75 | L13: =Plan!Q13 -> 1428571.4 | M13: =Plan!O13 -> 3.5 | N13: =IF(OR(H13=0,Plan!L13="Sin costo"),"",J13/H13*IF(Plan!L13="Por mil",1000,1)) -> 4.2373833 | O13: =IF(L13=0,"",H13/L13) -> 0.8244348 | P13: =I13-J13 -> 9.3625 | Q13: =P13/Insights!$B$7 -> 1.1926752 | R13: =IF(OR(M13=0,N13=""),"",N13/M13) -> 1.2106809 | S13: =MAX(0,MIN(Insights!$B$8,Plan!G13)-Plan!F13+1) -> 7 | T13: =I13/Plan!R13 -> 714.28571 | U13: =IF(S13=0,"",J13/S13) -> 712.94821 | V13: =L13/Plan!R13 -> 204081.63 | W13: =IF(S13=0,"",H13/S13) -> 168252 | X13: =IF(S13=0,"Sin iniciar",IF(J13>I13*1.05,"Gastó de más",IF(AND(O13<>"",O13<0.8),"Bajo proyección",IF(AND(R13<>"",R13>1.2),"Costo alto","En línea")))) -> Costo alto
A14: =Plan!A14 -> ELE2609-010 | B14: =Plan!E14 -> Electro Independencia | C14: =Plan!I14 -> Basis | D14: =Plan!J14 -> Display programático | E14: =Plan!K14 -> Programatic | F14: =IFERROR(VLOOKUP(C14,Catálogos!$E$4:$G$12,3,FALSE()),"Revisar medio") -> USD | G14: 547.64 | H14: 894893 | I14: =Plan!M14 -> 4300 | J14: =IF(F14="USD",G14*Insights!$B$7,G14) -> 4298.974 | K14: =J14/Insights!$B$7 -> 547.64 | L14: =Plan!Q14 -> 694668.82 | M14: =Plan!O14 -> 6.19 | N14: =IF(OR(H14=0,Plan!L14="Sin costo"),"",J14/H14*IF(Plan!L14="Por mil",1000,1)) -> 4.8038972 | O14: =IF(L14=0,"",H14/L14) -> 1.2882297 | P14: =I14-J14 -> 1.026 | Q14: =P14/Insights!$B$7 -> 0.13070064 | R14: =IF(OR(M14=0,N14=""),"",N14/M14) -> 0.77607387 | S14: =MAX(0,MIN(Insights!$B$8,Plan!G14)-Plan!F14+1) -> 7 | T14: =I14/Plan!R14 -> 614.28571 | U14: =IF(S14=0,"",J14/S14) -> 614.13914 | V14: =L14/Plan!R14 -> 99238.403 | W14: =IF(S14=0,"",H14/S14) -> 127841.86 | X14: =IF(S14=0,"Sin iniciar",IF(J14>I14*1.05,"Gastó de más",IF(AND(O14<>"",O14<0.8),"Bajo proyección",IF(AND(R14<>"",R14>1.2),"Costo alto","En línea")))) -> En línea
A15: =Plan!A15 -> ELE2609-011 | B15: =Plan!E15 -> Electro Independencia | C15: =Plan!I15 -> Google Ads | D15: =Plan!J15 -> Demand Gen · Alcance | E15: =Plan!K15 -> Google | F15: =IFERROR(VLOOKUP(C15,Catálogos!$E$4:$G$12,3,FALSE()),"Revisar medio") -> USD | G15: 350.17 | H15: 336884 | I15: =Plan!M15 -> 2756.61 | J15: =IF(F15="USD",G15*Insights!$B$7,G15) -> 2748.8345 | K15: =J15/Insights!$B$7 -> 350.17 | L15: =Plan!Q15 -> 352507.67 | M15: =Plan!O15 -> 7.82 | N15: =IF(OR(H15=0,Plan!L15="Sin costo"),"",J15/H15*IF(Plan!L15="Por mil",1000,1)) -> 8.1595876 | O15: =IF(L15=0,"",H15/L15) -> 0.95567849 | P15: =I15-J15 -> 7.7755 | Q15: =P15/Insights!$B$7 -> 0.99050955 | R15: =IF(OR(M15=0,N15=""),"",N15/M15) -> 1.0434255 | S15: =MAX(0,MIN(Insights!$B$8,Plan!G15)-Plan!F15+1) -> 7 | T15: =I15/Plan!R15 -> 393.80143 | U15: =IF(S15=0,"",J15/S15) -> 392.69064 | V15: =L15/Plan!R15 -> 50358.239 | W15: =IF(S15=0,"",H15/S15) -> 48126.286 | X15: =IF(S15=0,"Sin iniciar",IF(J15>I15*1.05,"Gastó de más",IF(AND(O15<>"",O15<0.8),"Bajo proyección",IF(AND(R15<>"",R15>1.2),"Costo alto","En línea")))) -> En línea
A16: =Plan!A16 -> ELE2609-012 | B16: =Plan!E16 -> Electro Independencia | C16: =Plan!I16 -> Claro | D16: =Plan!J16 -> SMS geolocalizado | E16: =Plan!K16 -> Programatic | F16: =IFERROR(VLOOKUP(C16,Catálogos!$E$4:$G$12,3,FALSE()),"Revisar medio") -> GTQ | G16: 999.999 | H16: 12987 | I16: =Plan!M16 -> 1000 | J16: =IF(F16="USD",G16*Insights!$B$7,G16) -> 999.999 | K16: =J16/Insights!$B$7 -> 127.38841 | L16: =Plan!Q16 -> 12987.013 | M16: =Plan!O16 -> 77 | N16: =IF(OR(H16=0,Plan!L16="Sin costo"),"",J16/H16*IF(Plan!L16="Por mil",1000,1)) -> 77 | O16: =IF(L16=0,"",H16/L16) -> 0.999999 | P16: =I16-J16 -> 0.001 | Q16: =P16/Insights!$B$7 -> 0.00012738854 | R16: =IF(OR(M16=0,N16=""),"",N16/M16) -> 1 | S16: =MAX(0,MIN(Insights!$B$8,Plan!G16)-Plan!F16+1) -> 1 | T16: =I16/Plan!R16 -> 1000 | U16: =IF(S16=0,"",J16/S16) -> 999.999 | V16: =L16/Plan!R16 -> 12987.013 | W16: =IF(S16=0,"",H16/S16) -> 12987 | X16: =IF(S16=0,"Sin iniciar",IF(J16>I16*1.05,"Gastó de más",IF(AND(O16<>"",O16<0.8),"Bajo proyección",IF(AND(R16<>"",R16>1.2),"Costo alto","En línea")))) -> En línea
... A30: =Plan!A30 -> ELE2608-002 | B30: =Plan!E30 -> Mantenimiento | C30: =Plan!I30 -> Meta | D30: =Plan!J30 -> Interacción | E30: =Plan!K30 -> Meta FB e IG | F30: =IFERROR(VLOOKUP(C30,Catálogos!$E$4:$G$12,3,FALSE()),"Revisar medio") -> USD | G30: 9.16 | H30: 0 | I30: =Plan!M30 -> 0 | J30: =IF(F30="USD",G30*Insights!$B$7,G30) -> 71.906 | K30: =J30/Insights!$B$7 -> 9.16 | L30: =Plan!Q30 -> 0 | M30: =Plan!O30 -> 0.3 | N30: =IF(OR(H30=0,Plan!L30="Sin costo"),"",J30/H30*IF(Plan!L30="Por mil",1000,1)) | O30: =IF(L30=0,"",H30/L30) | P30: =I30-J30 -> -71.906 | Q30: =P30/Insights!$B$7 -> -9.16 | R30: =IF(OR(M30=0,N30=""),"",N30/M30) | S30: =MAX(0,MIN(Insights!$B$8,Plan!G30)-Plan!F30+1) -> 30 | T30: =I30/Plan!R30 -> 0 | U30: =IF(S30=0,"",J30/S30) -> 2.3968667 | V30: =L30/Plan!R30 -> 0 | W30: =IF(S30=0,"",H30/S30) -> 0 | X30: =IF(S30=0,"Sin iniciar",IF(J30>I30*1.05,"Gastó de más",IF(AND(O30<>"",O30<0.8),"Bajo proyección",IF(AND(R30<>"",R30>1.2),"Costo alto","En línea")))) -> Gastó de más
A31: Total | I31: =SUM(I5:I30) -> 66148.336 | J31: =SUM(J5:J30) -> 63153.173 | K31: =SUM(K5:K30) -> 8044.9903 | P31: =SUM(P5:P30) -> 2995.1625 | Q31: =SUM(Q5:Q30) -> 381.54936
A33: Gastado total en el Excel original: Q63,153.10. Puede variar unos quetzales por redondeo al convertir de $ a Q.

Sheet Resumen
A1: Resumen · Electroma · Septiembre 2026
A3: Por actividad | B3: Inversión Q | C3: % del plan | D3: Gastado Q | E3: % ejecutado
A4: Mantenimiento | B4: =SUMIF(Plan!$E$5:$E$30,A4,Plan!$M$5:$M$30) -> 10215 | C4: =IF($B$12=0,0,B4/$B$12) -> 0.15442565 | D4: =SUMIF(Control!$B$5:$B$30,A4,Control!$J$5:$J$30) -> 9055.446 | E4: =IF(B4=0,"",D4/B4) -> 0.88648517
A5: Apoyo CC | B5: =SUMIF(Plan!$E$5:$E$30,A5,Plan!$M$5:$M$30) -> 3500 | C5: =IF($B$12=0,0,B5/$B$12) -> 0.052911384 | D5: =SUMIF(Control!$B$5:$B$30,A5,Control!$J$5:$J$30) -> 3496.547 | E5: =IF(B5=0,"",D5/B5) -> 0.99901343
A6: Promo CC | B6: =SUMIF(Plan!$E$5:$E$30,A6,Plan!$M$5:$M$30) -> 2000.023 | C6: =IF($B$12=0,0,B6/$B$12) -> 0.030235424 | D6: =SUMIF(Control!$B$5:$B$30,A6,Control!$J$5:$J$30) -> 1999.7875 | E6: =IF(B6=0,"",D6/B6) -> 0.99988225
A7: Electro Independencia | B7: =SUMIF(Plan!$E$5:$E$30,A7,Plan!$M$5:$M$30) -> 36910.79 | C7: =IF($B$12=0,0,B7/$B$12) -> 0.55800028 | D7: =SUMIF(Control!$B$5:$B$30,A7,Control!$J$5:$J$30) -> 35630.516 | E7: =IF(B7=0,"",D7/B7) -> 0.96531438
A8: Electro Days | B8: =SUMIF(Plan!$E$5:$E$30,A8,Plan!$M$5:$M$30) -> 9065 | C8: =IF($B$12=0,0,B8/$B$12) -> 0.13704048 | D8: =SUMIF(Control!$B$5:$B$30,A8,Control!$J$5:$J$30) -> 8544.2505 | E8: =IF(B8=0,"",D8/B8) -> 0.94255383
A9: Talento Humano | B9: =SUMIF(Plan!$E$5:$E$30,A9,Plan!$M$5:$M$30) -> 392.5 | C9: =IF($B$12=0,0,B9/$B$12) -> 0.0059336338 | D9: =SUMIF(Control!$B$5:$B$30,A9,Control!$J$5:$J$30) -> 391.6365 | E9: =IF(B9=0,"",D9/B9) -> 0.9978
A10: Leads B2B | B10: =SUMIF(Plan!$E$5:$E$30,A10,Plan!$M$5:$M$30) -> 2000.023 | C10: =IF($B$12=0,0,B10/$B$12) -> 0.030235424 | D10: =SUMIF(Control!$B$5:$B$30,A10,Control!$J$5:$J$30) -> 1997.668 | E10: =IF(B10=0,"",D10/B10) -> 0.99882251
A11: Capacitación | B11: =SUMIF(Plan!$E$5:$E$30,A11,Plan!$M$5:$M$30) -> 2065 | C11: =IF($B$12=0,0,B11/$B$12) -> 0.031217716 | D11: =SUMIF(Control!$B$5:$B$30,A11,Control!$J$5:$J$30) -> 2037.3215 | E11: =IF(B11=0,"",D11/B11) -> 0.98659637
A12: Total | B12: =SUM(B4:B11) -> 66148.336 | C12: =SUM(C4:C11) -> 1 | D12: =SUM(D4:D11) -> 63153.173 | E12: =IF(B12=0,"",D12/B12) -> 0.95472052
A15: Por partida de presupuesto | B15: Disponible Q | C15: Planeado Q | D15: Gastado Q | E15: Disponible − planeado | F15: Planeado − gastado
A16: Meta FB e IG | B16: =IFERROR(VLOOKUP(A16,Insights!$A$12:$D$23,4,FALSE()),0) -> 30672.463 | C16: =SUMIF(Plan!$K$5:$K$30,A16,Plan!$M$5:$M$30) -> 27215.023 | D16: =SUMIF(Control!$E$5:$E$30,A16,Control!$J$5:$J$30) -> 27199.543 | E16: =B16-C16 -> 3457.4396 | F16: =C16-D16 -> 15.4795
A17: Google | B17: =IFERROR(VLOOKUP(A17,Insights!$A$12:$D$23,4,FALSE()),0) -> 3917.0755 | C17: =SUMIF(Plan!$K$5:$K$30,A17,Plan!$M$5:$M$30) -> 9256.61 | D17: =SUMIF(Control!$E$5:$E$30,A17,Control!$J$5:$J$30) -> 9372.272 | E17: =B17-C17 -> -5339.5345 | F17: =C17-D17 -> -115.662
A18: YouTube | B18: =IFERROR(VLOOKUP(A18,Insights!$A$12:$D$23,4,FALSE()),0) -> -8957.3265 | C18: =SUMIF(Plan!$K$5:$K$30,A18,Plan!$M$5:$M$30) -> 5000 | D18: =SUMIF(Control!$E$5:$E$30,A18,Control!$J$5:$J$30) -> 4990.6375 | E18: =B18-C18 -> -13957.326 | F18: =C18-D18 -> 9.3625
A19: LinkedIn | B19: =IFERROR(VLOOKUP(A19,Insights!$A$12:$D$23,4,FALSE()),0) -> 9000.6165 | C19: =SUMIF(Plan!$K$5:$K$30,A19,Plan!$M$5:$M$30) -> 1065 | D19: =SUMIF(Control!$E$5:$E$30,A19,Control!$J$5:$J$30) -> 1037.31 | E19: =B19-C19 -> 7935.6165 | F19: =C19-D19 -> 27.69
A20: Programatic | B20: =IFERROR(VLOOKUP(A20,Insights!$A$12:$D$23,4,FALSE()),0) -> 1272.383 | C20: =SUMIF(Plan!$K$5:$K$30,A20,Plan!$M$5:$M$30) -> 6300 | D20: =SUMIF(Control!$E$5:$E$30,A20,Control!$J$5:$J$30) -> 6298.972 | E20: =B20-C20 -> -5027.617 | F20: =C20-D20 -> 1.028
A21: Claro SMS | B21: =IFERROR(VLOOKUP(A21,Insights!$A$12:$D$23,4,FALSE()),0) -> -609.28 | C21: =SUMIF(Plan!$K$5:$K$30,A21,Plan!$M$5:$M$30) -> 1600 | D21: =SUMIF(Control!$E$5:$E$30,A21,Control!$J$5:$J$30) -> 1600 | E21: =B21-C21 -> -2209.28 | F21: =C21-D21 -> 0
A22: Whatsapp Isoft | B22: =IFERROR(VLOOKUP(A22,Insights!$A$12:$D$23,4,FALSE()),0) -> -3807.5221 | C22: =SUMIF(Plan!$K$5:$K$30,A22,Plan!$M$5:$M$30) -> 3865 | D22: =SUMIF(Control!$E$5:$E$30,A22,Control!$J$5:$J$30) -> 3424.33 | E22: =B22-C22 -> -7672.5221 | F22: =C22-D22 -> 440.67
A23: Tik Tok | B23: =IFERROR(VLOOKUP(A23,Insights!$A$12:$D$23,4,FALSE()),0) -> 12819.531 | C23: =SUMIF(Plan!$K$5:$K$30,A23,Plan!$M$5:$M$30) -> 8454.18 | D23: =SUMIF(Control!$E$5:$E$30,A23,Control!$J$5:$J$30) -> 5840.7925 | E23: =B23-C23 -> 4365.3515 | F23: =C23-D23 -> 2613.3875
A24: Leads B2B | B24: =IFERROR(VLOOKUP(A24,Insights!$A$12:$D$23,4,FALSE()),0) -> 13137.887 | C24: =SUMIF(Plan!$K$5:$K$30,A24,Plan!$M$5:$M$30) -> 2000.023 | D24: =SUMIF(Control!$E$5:$E$30,A24,Control!$J$5:$J$30) -> 1997.668 | E24: =B24-C24 -> 11137.864 | F24: =C24-D24 -> 2.355
A25: Tráfico a tiendas Geolocalizado | B25: =IFERROR(VLOOKUP(A25,Insights!$A$12:$D$23,4,FALSE()),0) -> 7360.7583 | C25: =SUMIF(Plan!$K$5:$K$30,A25,Plan!$M$5:$M$30) -> 1000 | D25: =SUMIF(Control!$E$5:$E$30,A25,Control!$J$5:$J$30) -> 1000.0115 | E25: =B25-C25 -> 6360.7583 | F25: =C25-D25 -> -0.0115
A26: Mundial | B26: =IFERROR(VLOOKUP(A26,Insights!$A$12:$D$23,4,FALSE()),0) -> -4057.263 | C26: =SUMIF(Plan!$K$5:$K$30,A26,Plan!$M$5:$M$30) -> 0 | D26: =SUMIF(Control!$E$5:$E$30,A26,Control!$J$5:$J$30) -> 0 | E26: =B26-C26 -> -4057.263 | F26: =C26-D26 -> 0
A27: Extras | B27: =IFERROR(VLOOKUP(A27,Insights!$A$12:$D$23,4,FALSE()),0) -> 0 | C27: =SUMIF(Plan!$K$5:$K$30,A27,Plan!$M$5:$M$30) -> 392.5 | D27: =SUMIF(Control!$E$5:$E$30,A27,Control!$J$5:$J$30) -> 391.6365 | E27: =B27-C27 -> -392.5 | F27: =C27-D27 -> 0.8635
A28: Total | B28: =SUM(B16:B27) -> 60749.323 | C28: =SUM(C16:C27) -> 66148.336 | D28: =SUM(D16:D27) -> 63153.173 | E28: =SUM(E16:E27) -> -5399.0129 | F28: =SUM(F16:F27) -> 2995.1625
A31: Por medio | B31: Planeado Q | C31: Gastado Q | D31: % ejecutado
A32: Meta | B32: =SUMIF(Plan!$I$5:$I$30,A32,Plan!$M$5:$M$30) -> 30607.546 | C32: =SUMIF(Control!$C$5:$C$30,A32,Control!$J$5:$J$30) -> 30588.859 | D32: =IF(B32=0,"",C32/B32) -> 0.99938948
A33: Google Ads | B33: =SUMIF(Plan!$I$5:$I$30,A33,Plan!$M$5:$M$30) -> 9256.61 | C33: =SUMIF(Control!$C$5:$C$30,A33,Control!$J$5:$J$30) -> 9372.272 | D33: =IF(B33=0,"",C33/B33) -> 1.0124951
A34: YouTube | B34: =SUMIF(Plan!$I$5:$I$30,A34,Plan!$M$5:$M$30) -> 5000 | C34: =SUMIF(Control!$C$5:$C$30,A34,Control!$J$5:$J$30) -> 4990.6375 | D34: =IF(B34=0,"",C34/B34) -> 0.9981275
A35: TikTok | B35: =SUMIF(Plan!$I$5:$I$30,A35,Plan!$M$5:$M$30) -> 8454.18 | C35: =SUMIF(Control!$C$5:$C$30,A35,Control!$J$5:$J$30) -> 5840.7925 | D35: =IF(B35=0,"",C35/B35) -> 0.69087629
A36: LinkedIn | B36: =SUMIF(Plan!$I$5:$I$30,A36,Plan!$M$5:$M$30) -> 0 | C36: =SUMIF(Control!$C$5:$C$30,A36,Control!$J$5:$J$30) -> 0 | D36: =IF(B36=0,"",C36/B36)
A37: Basis | B37: =SUMIF(Plan!$I$5:$I$30,A37,Plan!$M$5:$M$30) -> 4300 | C37: =SUMIF(Control!$C$5:$C$30,A37,Control!$J$5:$J$30) -> 4298.974 | D37: =IF(B37=0,"",C37/B37) -> 0.9997614
A38: Claro | B38: =SUMIF(Plan!$I$5:$I$30,A38,Plan!$M$5:$M$30) -> 3600 | C38: =SUMIF(Control!$C$5:$C$30,A38,Control!$J$5:$J$30) -> 3599.998 | D38: =IF(B38=0,"",C38/B38) -> 0.99999944
A39: iSoft | B39: =SUMIF(Plan!$I$5:$I$30,A39,Plan!$M$5:$M$30) -> 4930 | C39: =SUMIF(Control!$C$5:$C$30,A39,Control!$J$5:$J$30) -> 4461.64 | D39: =IF(B39=0,"",C39/B39) -> 0.90499797
A40: Mailjet | B40: =SUMIF(Plan!$I$5:$I$30,A40,Plan!$M$5:$M$30) -> 0 | C40: =SUMIF(Control!$C$5:$C$30,A40,Control!$J$5:$J$30) -> 0 | D40: =IF(B40=0,"",C40/B40)
A41: Total | B41: =SUM(B32:B40) -> 66148.336 | C41: =SUM(C32:C40) -> 63153.173 | D41: =IF(B41=0,"",C41/B41) -> 0.95472052
A43: El resumen 'por medio' del Excel original en realidad era por partida de presupuesto; aquí quedan separados.

Sheet Revisar
A1: Diferencias encontradas al migrar · confirmar con el equipo
A3: # | B3: Línea | C3: Qué encontré | D3: Cómo quedó en este archivo | E3: Confirmación del equipo
A4: 1 | B4: ELE2609-006 Promo CC | C4: Con costo Q4.00 el proyectado es 500, pero el Excel decía 625 (equivale a Q3.20). | D4: Costo Q4.00 y proyectado 500. | E4: Confirmado: costo Q4.00, proyectado 500.
A5: 2 | B5: ELE2609-011 Demand Gen Electro Independencia | C5: La inversión decía Q2,302.40 pero en dólares $351.16 (= Q2,756.61). Se gastaron Q2,748.83. | D5: Inversión corregida a Q2,756.61; el proyectado pasa a 352,507. | E5: Confirmado: Q2,756.61 era el monto correcto.
A6: 3 | B6: ELE2609-011 y ELE2609-017 Demand Gen | C6: El mismo objetivo 'Dmand Gen' se usó por mil (alcance, Q7.82) y por unidad (Q0.035). | D6: Se separó en 'Demand Gen · Alcance' (por mil) y 'Demand Gen · Tráfico' (por unidad). | E6: Confirmado: Electro Days medía clics. Demand Gen ha salido más caro últimamente (real Q0.179 vs Q0.035 estimado): actualizar el costo de referencia en noviembre.
A7: 4 | B7: ELE2609-025 WhatsApp Capacitación | C7: En el resumen por medio aparecía como 'LinkedIn' (Q1,065). | D7: Se dejó la partida LinkedIn, porque así se cargó al presupuesto. | E7: ¿Se tomó presupuesto de LinkedIn a propósito?
A8: 5 | B8: ELE2609-012/013 SMS geolocalizado | C8: Se cargaron a la partida 'Programatic'. | D8: Partida Programatic. | E8: ¿Correcto?
A9: 6 | B9: ELE2609-024 Tráfico Capacitación | C9: Se cargó a la partida 'Tráfico a tiendas'. | D9: Partida Tráfico a tiendas Geolocalizado. | E9: ¿Correcto?
A10: 7 | B10: Envíos en días sueltos | C10: WhatsApp y Mailing con fechas '13 y 17' o '20 y 24'. | D10: Una sola línea con inicio y fin, y los días en 'Fechas de envío'. | E10: ¿Prefieren una línea por envío?
A11: 8 | B11: Mailjet | C11: Costo Q0 con proyectado fijo de 4,500. | D11: Objetivo 'Mailing' sin costo; el proyectado se captura en 'Proyectado manual'. | E11: —
A12: 9 | B12: Varias líneas | C12: Costos escritos como texto ('Q3.500') generaban error en Opt Costo. | D12: Todos los costos quedaron como número. | E12: —
A13: 10 | B13: Presupuesto | C13: El plan (Q66,148.34) supera lo disponible del mes (Q60,749.32). | D13: Se ve en Resumen, columna 'Disponible − planeado'. | E13: ¿Había un monto extra aprobado?
A14: 11 | B14: Continuaciones de agosto | C14: Search (003), Apoyo CC (006) y Leads B2B (023) de agosto siguieron corriendo en septiembre. | D14: Las líneas de septiembre conservan su código de agosto: ELE2608-003, ELE2608-006 y ELE2608-023. | E14: Confirmado con Porter: el gasto coincide.
A15: 12 | B15: ELE2608-002 arrastre | C15: La Interacción de agosto gastó $9.16 en septiembre; el Excel lo sumaba a la Interacción nueva. | D15: Línea de arrastre con inversión cero. La 002 de septiembre queda con $335.65; su resultado aún incluye el arrastre. | E15: Merkl separará el resultado exacto al conectar Porter.
A16: 13 | B16: KPIs | C16: La meta 2026 venía vacía. | D16: Columna 'Meta 2026' lista para llenar en Insights. | E16: Definir metas.
